{
  "id": "98930c8d-3dab-406e-b19b-a640b34949cf",
  "schema_version": "3.0",
  "source_type": "repo",
  "source": "public-apis/public-apis",
  "slug": "public-apis_public-apis",
  "title": "public-apis_public-apis",
  "analyzed_at": "2026-04-09T10:47:45.073Z",
  "depth": "quick",
  "tags": [
    "repo",
    "curated-list",
    "public",
    "apis",
    "python",
    "api",
    "dataset",
    "development",
    "free"
  ],
  "scoring": {
    "quality_band": "Needs Work",
    "quality_score": 42,
    "personal_fit_band": "Needs Work",
    "personal_fit_score": 48,
    "classification": "park-for-later"
  },
  "summary": "This repo understands that developers need a single, searchable catalog of free APIs organized by domain.  The structured format (API|Description|Auth|HTTPS|CORS) is machine-parseable by design.",
  "creator_view": "This repo understands that developers need a single, searchable catalog of free APIs organized by domain. The structured format (API|Description|Auth|HTTPS|CORS) is machine-parseable by design. The Python validation scripts enforce format consistency at PR time — a quality gate that codecrafters lacks.",
  "candidates": [],
  "last_synthesized_at": null,
  "repo": "public-apis/public-apis",
  "url": "https://github.com/public-apis/public-apis",
  "skillVersion": "4.1",
  "scanDepth": "standard",
  "date": "2026-04-06",
  "repoType": "curated-list",
  "classification": {
    "type": "curated-list",
    "confidence": "high",
    "signals": [
      "API catalog in README",
      "40+ categories",
      "1490 entries",
      "format validation scripts"
    ]
  },
  "metadata": {
    "stars": 419594,
    "forks": 45644,
    "openIssues": 1197,
    "contributors": 30,
    "language": "Python",
    "languages": {
      "Python": 40479,
      "Shell": 1352
    },
    "license": "MIT",
    "created": "2016-03-20T23:49:42Z",
    "lastPush": "2026-03-18T16:28:22Z",
    "size": 4962,
    "topics": [
      "api",
      "apis",
      "dataset",
      "development",
      "free",
      "list",
      "lists",
      "open-source",
      "public",
      "public-api",
      "public-apis",
      "resources",
      "software"
    ],
    "defaultBranch": "master",
    "recentCommits90d": 1,
    "openPRs": 1,
    "releases": 0
  },
  "dimensions": {
    "QS-01-stars": {
      "value": 419594,
      "band": "Exceptional"
    },
    "QS-02-forks": {
      "value": 45644,
      "band": "Exceptional"
    },
    "QS-03-openIssues": {
      "value": 1197,
      "band": "Very High"
    },
    "QS-04-recentCommits": {
      "value": 1,
      "band": "Very Low"
    },
    "QS-05-contributors": {
      "value": 30,
      "band": "Moderate"
    },
    "QS-06-language": {
      "value": "Python",
      "band": "Dual"
    },
    "QS-07-license": {
      "value": "MIT",
      "band": "Strong"
    },
    "QS-08-lastPush": {
      "value": "2026-03-18",
      "band": "Moderately Stale",
      "daysSince": 19
    },
    "QS-09-age": {
      "value": "2016-03-20",
      "band": "Mature",
      "years": 10
    },
    "QS-10-size": {
      "value": 4962,
      "band": "Small"
    },
    "QS-11-topics": {
      "value": 13,
      "band": "Well-Tagged"
    },
    "QS-12-wiki": {
      "value": false
    },
    "QS-13-pages": {
      "value": false
    },
    "QS-14-releases": {
      "value": 0,
      "band": "None"
    },
    "QS-15-openPRs": {
      "value": 1,
      "band": "Low"
    },
    "QS-16-forkRatio": {
      "value": 0.109,
      "band": "Normal"
    },
    "QS-17-issueToStar": {
      "value": 0.0029,
      "band": "Low"
    },
    "QS-18-description": {
      "value": "present",
      "band": "Good"
    }
  },
  "summaryBands": {
    "security": {
      "band": "Good",
      "score": 65,
      "note": "MIT license. Python validation scripts with no obvious injection vectors."
    },
    "reliability": {
      "band": "Moderate",
      "score": 50,
      "note": "3 CI workflows + tests. But 1 commit in 90 days — maintenance declining."
    },
    "maintainability": {
      "band": "Moderate",
      "score": 55,
      "note": "1,490 entries in single README. Format validation scripts help. Link rot inevitable at scale."
    },
    "documentation": {
      "band": "Strong",
      "score": 75,
      "note": "CONTRIBUTING.md with structured format. 40+ categories. Well-tagged."
    },
    "process": {
      "band": "Weak",
      "score": 25,
      "note": "1,197 open issues. PRs bottlenecked. Commercial overlay (APILayer). No releases."
    },
    "velocity": {
      "band": "Very Low",
      "score": 10,
      "note": "1 commit in 90 days. 10 years old. Celebrity stagnation."
    }
  },
  "absencePattern": {
    "type": "celebrity-stagnation",
    "description": "420K stars, 1,197 open issues, 1 commit/90 days. Commercial capture by APILayer. PR approval bottleneck. Same pattern as codecrafters but with more infrastructure (validation scripts, CI)."
  },
  "creatorLens": "This repo understands that developers need a single, searchable catalog of free APIs organized by domain. The structured format (API|Description|Auth|HTTPS|CORS) is machine-parseable by design. The Python validation scripts enforce format consistency at PR time — a quality gate that codecrafters lacks."
}
